{
  "manifest": {
    "apis": {
      "custom": {
        "endpoint": {
          "uri": "arn:aws:lambda:us-east-1:933687065247:function:2d76ff1c-eec5-4018-892e-409f423b0de8:Release_0"
        },
        "interfaces": [],
        "locales": {},
        "regions": {
          "NA": {
            "endpoint": {
              "uri": "arn:aws:lambda:us-east-1:933687065247:function:2d76ff1c-eec5-4018-892e-409f423b0de8:Release_0"
            }
          },
          "EU": {
            "endpoint": {
              "uri": "arn:aws:lambda:eu-west-1:933687065247:function:2d76ff1c-eec5-4018-892e-409f423b0de8:Release_0"
            }
          },
          "FE": {
            "endpoint": {
              "uri": "arn:aws:lambda:us-west-2:933687065247:function:2d76ff1c-eec5-4018-892e-409f423b0de8:Release_0"
            }
          }
        }
      }
    },
    "manifestVersion": "1.0",
    "publishingInformation": {
      "distributionCountries": [],
      "isAvailableWorldwide": true,
      "locales": {
        "en-US": {
          "description": "Sample Full Description",
          "examplePhrases": [
            "Alexa open hello world",
            "hello",
            "help"
          ],
          "keywords": [],
          "name": "zodiac sign",
          "summary": "Sample Short Description"
        },
        "en-CA": {
          "description": "Sample Full Description",
          "examplePhrases": [
            "Alexa open hello world",
            "hello",
            "help"
          ],
          "keywords": [],
          "name": "zodiac sign",
          "summary": "Sample Short Description"
        },
        "en-IN": {
          "description": "Sample Full Description",
          "examplePhrases": [
            "Alexa open hello world",
            "hello",
            "help"
          ],
          "keywords": [],
          "name": "zodiac sign",
          "summary": "Sample Short Description"
        },
        "en-AU": {
          "description": "Sample Full Description",
          "examplePhrases": [
            "Alexa open hello world",
            "hello",
            "help"
          ],
          "keywords": [],
          "name": "zodiac sign",
          "summary": "Sample Short Description"
        },
        "en-GB": {
          "description": "Sample Full Description",
          "examplePhrases": [
            "Alexa open hello world",
            "hello",
            "help"
          ],
          "keywords": [],
          "name": "zodiac sign",
          "summary": "Sample Short Description"
        }
      },
      "testingInstructions": "Sample Testing Instructions."
    }
  }
}